{
  "epic": [
    {
      "name": "Итачи Учиха",
      "element": "Огонь 🔥",
      "rating": 80
    },
    {
      "name": "Какузу", 
      "element": "Земля 🌍",
      "rating": 80
    }
  ],
  "legendary": [
    {
      "name": "Пеин",
      "element": "Все стихии 🌟",
      "rating": 87
    }
  ],
  "myfics": [
    {
      "name": "Хаширама Сенджу",
      "element": "Дерево 🍃",
      "rating": 99
    }
  ],
  "adamant": [
    {
      "name": "Ичиго Куросаки",
      "element": "Духовная энергия ⚡",
      "rating": 101
    }
  ]
}
